fpgaconvnet/__init__.py
fpgaconvnet/hls/__init__.py
fpgaconvnet/hls/generate/__init__.py
fpgaconvnet/hls/generate/network.py
fpgaconvnet/hls/generate/partition.py
fpgaconvnet/hls/generate/partition_template.py
fpgaconvnet/hls/generate/util.py
fpgaconvnet/hls/generate/layers/__init__.py
fpgaconvnet/hls/generate/layers/convolution.py
fpgaconvnet/hls/generate/layers/inner_product.py
fpgaconvnet/hls/generate/layers/pooling.py
fpgaconvnet/hls/generate/layers/relu.py
fpgaconvnet/hls/generate/layers/squeeze.py
fpgaconvnet/hls/generate/modules/__init__.py
fpgaconvnet/hls/generate/modules/accum.py
fpgaconvnet/hls/generate/modules/bias.py
fpgaconvnet/hls/generate/modules/conv.py
fpgaconvnet/hls/generate/modules/fork.py
fpgaconvnet/hls/generate/modules/glue.py
fpgaconvnet/hls/generate/modules/module.py
fpgaconvnet/hls/generate/modules/pool.py
fpgaconvnet/hls/generate/modules/relu.py
fpgaconvnet/hls/generate/modules/sliding_window.py
fpgaconvnet/hls/generate/modules/squeeze.py
fpgaconvnet/hls/hardware/accum.hpp
fpgaconvnet/hls/hardware/batch_norm.hpp
fpgaconvnet/hls/hardware/bias.hpp
fpgaconvnet/hls/hardware/common.hpp
fpgaconvnet/hls/hardware/common_tb.hpp
fpgaconvnet/hls/hardware/conv.hpp
fpgaconvnet/hls/hardware/fifo.hpp
fpgaconvnet/hls/hardware/fork.hpp
fpgaconvnet/hls/hardware/glue.hpp
fpgaconvnet/hls/hardware/mem_read.hpp
fpgaconvnet/hls/hardware/mem_write.hpp
fpgaconvnet/hls/hardware/pool.hpp
fpgaconvnet/hls/hardware/relu.hpp
fpgaconvnet/hls/hardware/sliding_window.hpp
fpgaconvnet/hls/hardware/squeeze.hpp
fpgaconvnet/hls/hardware/wr.hpp
fpgaconvnet/hls/scripts/hls/common.tcl
fpgaconvnet/hls/scripts/hls/create_partition_project.tcl
fpgaconvnet/hls/scripts/hls/export_design.tcl
fpgaconvnet/hls/scripts/hls/run_cosim.tcl
fpgaconvnet/hls/scripts/hls/run_csim.tcl
fpgaconvnet/hls/scripts/hls/run_csynth.tcl
fpgaconvnet/hls/scripts/hls/run_implementation.tcl
fpgaconvnet/hls/scripts/hls/tcl_getopt.tcl
fpgaconvnet/hls/tools/__init__.py
fpgaconvnet/hls/tools/array_init.py
fpgaconvnet_hls-0.1.2.dist-info/LICENSE
fpgaconvnet_hls-0.1.2.dist-info/METADATA
fpgaconvnet_hls-0.1.2.dist-info/WHEEL
fpgaconvnet_hls-0.1.2.dist-info/top_level.txt
fpgaconvnet_hls-0.1.2.dist-info/RECORD
