Metadata-Version: 2.1
Name: fpgaconvnet-hls
Version: 0.1.2
Summary: Optimiser for mapping convolutional neural network models to FPGA platforms.
Home-page: https://github.com/AlexMontgomerie/fpgaconvnet-hls
Author: Alex Montgomerie
Author-email: am9215@ic.ac.uk
Classifier: Programming Language :: Python :: 3
Classifier: Operating System :: OS Independent
Requires-Python: >=3.7
License-File: LICENSE
Requires-Dist: fpbinary
Requires-Dist: untangle
Requires-Dist: numpy
